pytorch-ipfs/__init__.py
pytorch-ipfs/checkpoint.py
pytorch-ipfs/dataset.py
pytorch-ipfs/parsers.py
pytorch-ipfs/utils.py
pytorchipfs/__init__.py
pytorchipfs/checkpoint.py
pytorchipfs/dataset.py
pytorchipfs/datasets.py
pytorchipfs/parsers.py
pytorchipfs/utils.py
pytorchipfs-1.0.1.dist-info/LICENSE
pytorchipfs-1.0.1.dist-info/METADATA
pytorchipfs-1.0.1.dist-info/WHEEL
pytorchipfs-1.0.1.dist-info/top_level.txt
pytorchipfs-1.0.1.dist-info/RECORD
